sopel_weather/__init__.py
sopel_weather/providers/__init__.py
sopel_weather/providers/weather/__init__.py
sopel_weather/providers/weather/openmeteo.py
sopel_weather/providers/weather/openweathermap.py
sopel_weather/providers/weather/pirateweather.py
sopel_weather/providers/weather/tomorrow.py
sopel_weather-2.1.0.dist-info/licenses/LICENSE
sopel_weather-2.1.0.dist-info/METADATA
sopel_weather-2.1.0.dist-info/WHEEL
sopel_weather-2.1.0.dist-info/entry_points.txt
sopel_weather-2.1.0.dist-info/top_level.txt
sopel_weather-2.1.0.dist-info/RECORD
