Metadata-Version: 2.4
Name: sopel-weather
Version: 2.1.0
Summary: A weather lookup plugin for Sopel IRC bots
Author-email: Rusty Bower <rusty@rustybower.com>
License: MIT
Project-URL: Homepage, https://github.com/sopel-irc/sopel-weather
Project-URL: Bug Tracker, https://github.com/sopel-irc/sopel-weather/issues
Classifier: Development Status :: 5 - Production/Stable
Classifier: Intended Audience :: Developers
Classifier: Intended Audience :: System Administrators
Classifier: Programming Language :: Python :: 3 :: Only
Classifier: Programming Language :: Python :: 3.8
Classifier: Programming Language :: Python :: 3.9
Classifier: Programming Language :: Python :: 3.10
Classifier: Programming Language :: Python :: 3.11
Classifier: Programming Language :: Python :: 3.12
Classifier: Topic :: Communications :: Chat :: Internet Relay Chat
Requires-Python: >=3.8
License-File: LICENSE
Requires-Dist: sopel>=8.0
Requires-Dist: requests
Requires-Dist: pytz
Dynamic: license-file
